<?xml version="1.0" encoding="utf-16"?>
<ArrayOfExecutable>
  <Executable>
    <ProgramLocation>C:\MO\JobScheduler\iPSL.ICS.MO.JobScheduler.exe</ProgramLocation>
    <SolutionFolder>C:\SourceCode\iCE\MO\Window\Source\Job Scheduler\IPSL.MO.JobScheduler.sln</SolutionFolder>
  </Executable>
  <Executable>
    <ProgramLocation>C:\MO\Agents\IA\iPSL.ICS.MO.IA.Agent.exe</ProgramLocation>
    <SolutionFolder>C:\SourceCode\iCE\MO\Window\Source\Agents\iPSL.ICS.MO.IA.Agent\iPSL.ICS.MO.IA.Agent.sln</SolutionFolder>
  </Executable>
  <Executable>
    <ProgramLocation>C:\MO\Agents\FRED.R\iPSL.ICS.MO.FRED.ReceiveAgent.exe</ProgramLocation>
    <SolutionFolder>C:\SourceCode\iCE\MO\Window\Source\Agents\iPSL.ICS.MO.FRED.ReceiveAgent\iPSL.ICS.MO.FRED.ReceiveAgent.sln</SolutionFolder>
  </Executable>
  <Executable>
    <ProgramLocation>C:\MO\Agents\FRED.S\iPSL.ICS.MO.FRED.SendAgent.exe</ProgramLocation>
    <SolutionFolder>C:\SourceCode\iCE\MO\Window\Source\Agents\iPSL.ICS.MO.FRED.SendAgent\iPSL.ICS.MO.FRED.SendAgent.sln</SolutionFolder>
  </Executable>
  <Executable>
    <ProgramLocation>C:\MO\Agents\DEW.R\iPSL.ICS.MO.DEW.ReceiveAgent.exe</ProgramLocation>
    <SolutionFolder>C:\SourceCode\iCE\MO\Window\Source\Agents\iPSL.ICS.MO.DEW.ReceiveAgent\iPSL.ICS.MO.DEW.ReceiveAgent.sln</SolutionFolder>
  </Executable>
  <Executable>
    <ProgramLocation>C:\MO\Agents\DEW.S\iPSL.ICS.MO.DEW.SendAgent.exe</ProgramLocation>
    <SolutionFolder>C:\SourceCode\iCE\MO\Window\Source\Agents\iPSL.ICS.MO.DEW.SendAgent\iPSL.ICS.MO.DEW.SendAgent.sln</SolutionFolder>
  </Executable>
  <Executable>
    <ProgramLocation>C:\MO\Agents\KAPPA.R\iPSL.ICS.MO.KAPPA.ReceiveAgent.exe</ProgramLocation>
    <SolutionFolder>C:\SourceCode\iCE\MO\Window\Source\Agents\iPSL.ICS.MO.KAPPA.ReceiveAgent\iPSL.ICS.MO.KAPPA.ReceiveAgent.sln</SolutionFolder>
  </Executable>
  <Executable>
    <ProgramLocation>C:\MO\Agents\KAPPA.S\iPSL.ICS.MO.KAPPA.SendAgent.exe</ProgramLocation>
    <SolutionFolder>C:\SourceCode\iCE\MO\Window\Source\Agents\iPSL.ICS.MO.KAPPA.SendAgent\iPSL.ICS.MO.KAPPA.SendAgent.sln</SolutionFolder>
  </Executable>
  <Executable>
    <ProgramLocation>C:\MO\Agents\RNE.R\iPSL.ICS.MO.RNE.ReceiveAgent.exe</ProgramLocation>
    <SolutionFolder>C:\SourceCode\iCE\MO\Window\Source\Agents\iPSL.ICS.MO.RNE.ReceiveAgent\iPSL.ICS.MO.RNE.ReceiveAgent.sln</SolutionFolder>
  </Executable>
  <Executable>
    <ProgramLocation>C:\MO\Agents\RNE.S\iPSL.ICS.MO.RNE.SendAgent.exe</ProgramLocation>
    <SolutionFolder>C:\SourceCode\iCE\MO\Window\Source\Agents\iPSL.ICS.MO.RNE.SendAgent\iPSL.ICS.MO.RNE.SendAgent.sln</SolutionFolder>
  </Executable>
  <Executable>
    <ProgramLocation>C:\MO\Agents\SWITCH.R\iPSL.ICS.MO.Switch.ReceiveAgent.exe</ProgramLocation>
    <SolutionFolder>C:\SourceCode\iCE\MO\Window\Source\Agents\iPSL.ICS.MO.Switch.ReceiveAgent\iPSL.ICS.MO.Switch.ReceiveAgent.sln</SolutionFolder>
  </Executable>
  <Executable>
    <ProgramLocation>C:\MO\Agents\Switch.S\iPSL.ICS.MO.Switch.SendAgent.exe</ProgramLocation>
    <SolutionFolder>C:\SourceCode\iCE\MO\Window\Source\Agents\iPSL.ICS.MO.Switch.SendAgent\iPSL.ICS.MO.Switch.SendAgent.sln</SolutionFolder>
  </Executable>
  <Executable>
    <ProgramLocation>C:\MO\Agents\UpdateState\iPSL.ICS.MO.UpdateStateAgent.exe</ProgramLocation>
    <SolutionFolder>C:\SourceCode\iCE\MO\Window\Source\Agents\iPSL.ICS.MO.UpdateStateAgent\iPSL.ICS.MO.UpdateStateAgent.sln</SolutionFolder>
  </Executable>
  <Executable>
    <ProgramLocation>C:\MO\Agents\CASSI.R\iPSL.ICS.MO.CASSI.ReceiveAgent.exe</ProgramLocation>
    <SolutionFolder>C:\SourceCode\iCE\MO\Window\Source\Agents\iPSL.ICS.MO.CASSI.ReceiveAgent\iPSL.ICS.MO.CASSI.ReceiveAgent.sln</SolutionFolder>
  </Executable>
  <Executable>
    <ProgramLocation>C:\MO\Agents\CM.R\\iPSL.ICS.MO.CM.ReceiveAgent.exe</ProgramLocation>
    <SolutionFolder>C:\SourceCode\iCE\MO\Window\Source\Agents\iPSL.ICS.MO.CM.ReceiveAgent\iPSL.ICS.MO.CM.ReceiveAgent.sln</SolutionFolder>
  </Executable>
  <Executable>
    <ProgramLocation>C:\MO\Agents\CM.S\iPSL.ICS.MO.CM.SendAgent.exe</ProgramLocation>
    <SolutionFolder>C:\SourceCode\iCE\MO\Window\Source\Agents\iPSL.ICS.MO.CM.SendAgent\iPSL.ICS.MO.CM.SendAgent.sln</SolutionFolder>
  </Executable>
  <Executable>
    <ProgramLocation>C:\MO\Supervisor\iPSL.ICS.MO.Supervisor.exe</ProgramLocation>
    <SolutionFolder>C:\SourceCode\iCE\MO\Window\Source\Supervisor\iPSL.ICS.MO.Supervisor.sln</SolutionFolder>
  </Executable>
</ArrayOfExecutable>